alexandra_ai_eval/__init__.py
alexandra_ai_eval/automatic_speech_recognition.py
alexandra_ai_eval/cli.py
alexandra_ai_eval/co2.py
alexandra_ai_eval/config.py
alexandra_ai_eval/country_codes.py
alexandra_ai_eval/enums.py
alexandra_ai_eval/evaluator.py
alexandra_ai_eval/exceptions.py
alexandra_ai_eval/gui.py
alexandra_ai_eval/hf_hub_utils.py
alexandra_ai_eval/leaderboard_utils.py
alexandra_ai_eval/local_hf_utils.py
alexandra_ai_eval/local_pytorch_utils.py
alexandra_ai_eval/metric_configs.py
alexandra_ai_eval/model_adjustment.py
alexandra_ai_eval/model_loading.py
alexandra_ai_eval/named_entity_recognition.py
alexandra_ai_eval/question_answering.py
alexandra_ai_eval/scoring.py
alexandra_ai_eval/sequence_classification.py
alexandra_ai_eval/spacy_utils.py
alexandra_ai_eval/task.py
alexandra_ai_eval/task_configs.py
alexandra_ai_eval/task_factory.py
alexandra_ai_eval/utils.py
alexandra_ai_eval-0.1.0.dist-info/entry_points.txt
alexandra_ai_eval-0.1.0.dist-info/LICENSE
alexandra_ai_eval-0.1.0.dist-info/WHEEL
alexandra_ai_eval-0.1.0.dist-info/METADATA
alexandra_ai_eval-0.1.0.dist-info/RECORD
