Metadata-Version: 2.1
Name: alexandra-ai-eval
Version: 0.1.0
Summary: Evaluation of finetuned models.
License: MIT
Author: Dan Saattrup Nielsen
Author-email: dan.nielsen@alexandra.dk
Requires-Python: >=3.8,<3.11
Classifier: License :: OSI Approved :: MIT License
Classifier: Programming Language :: Python :: 3
Classifier: Programming Language :: Python :: 3.8
Classifier: Programming Language :: Python :: 3.9
Classifier: Programming Language :: Python :: 3.10
Requires-Dist: codecarbon (>=2.1.3,<3.0.0)
Requires-Dist: colorama (>=0.4.5,<1.0.0)
Requires-Dist: datasets (>=2.4.0,<3.0.0)
Requires-Dist: evaluate (>=0.3.0,<1.0.0)
Requires-Dist: fsspec (>=2022.7.1,<2023.0.0)
Requires-Dist: gradio (>=3.1.7,<4.0.0)
Requires-Dist: huggingface-hub (>=0.8.1,<1.0.0)
Requires-Dist: jiwer (>=2.5.1,<3.0.0)
Requires-Dist: librosa (>=0.9.2,<1.0.0)
Requires-Dist: protobuf (>=3.0.0,<3.21.0)
Requires-Dist: psutil (>=5.9.0,<5.9.2)
Requires-Dist: pyctcdecode (>=0.4.0,<1.0.0)
Requires-Dist: pypi-kenlm (>=0.1.20220713,<1.0.0)
Requires-Dist: sentencepiece (>=0.1.96,<1.0.0)
Requires-Dist: seqeval (>=1.2.2,<2.0.0)
Requires-Dist: soundfile (>=0.11.0,<1.0.0)
Requires-Dist: spacy (>=3.4.1,<4.0.0)
Requires-Dist: tabulate (>=0.9.0,<1.0.0)
Requires-Dist: termcolor (>=1.1.0,<2.0.0)
Requires-Dist: torch (>=1.13.1,<2.0.0)
Requires-Dist: torchaudio (>=0.13.1,<1.0.0)
Requires-Dist: tqdm (>=4.64.0,<5.0.0)
Requires-Dist: transformers (>=4.23.0,<5.0.0)
